{
  "generated_at": "2026-04-27 05:10",
  "game_date": "2026-04-26",
  "yesterday": [
    {
      "selection": "Texas A&M Aggies@Florida Gators UNDER 12.5",
      "sport": "baseball_ncaa",
      "market_type": "TOTAL",
      "side_type": "UNDER",
      "result": "WIN",
      "pnl_units": 4.76,
      "clv": -1.0,
      "edge_pct": 20.0,
      "odds": -105.0,
      "units": 5.0,
      "context_factors": "Sunday game | Florida Gators SP: Russell Sandefer (3.65 ERA) | Florida Gators allows 5.8 R/sunday | Texas A&M Aggies allows 3.7 R/sunday | Pitching edge: Texas A&M Aggies (-0.6 pts) | Steam: no movement",
      "context_confirmed": 1,
      "model_spread": 0.67,
      "closing_line": 13.5,
      "event_id": "36591cd404bf3a7b84e7c63c3290b396",
      "dt": "2026-04-26"
    },
    {
      "selection": "Virginia Cavaliers@Pittsburgh Panthers UNDER 15.0",
      "sport": "baseball_ncaa",
      "market_type": "TOTAL",
      "side_type": "UNDER",
      "result": "WIN",
      "pnl_units": 4.76,
      "clv": 0.0,
      "edge_pct": 20.0,
      "odds": -105.0,
      "units": 5.0,
      "context_factors": "Away slow-paced (-0.3) | Sunday game | Pittsburgh Panthers allows 6.0 R/sunday | Virginia Cavaliers allows 3.8 R/sunday | Pitching edge: Virginia Cavaliers (-0.7 pts) | Steam: no movement",
      "context_confirmed": 1,
      "model_spread": -3.1599999999999997,
      "closing_line": 15.0,
      "event_id": "f1a7c2091e8a3a07cff9d0ea33002906",
      "dt": "2026-04-26"
    },
    {
      "selection": "San Antonio Spurs@Portland Trail Blazers UNDER 219.0",
      "sport": "basketball_nba",
      "market_type": "TOTAL",
      "side_type": "DATA_TOTAL",
      "result": "WIN",
      "pnl_units": 4.55,
      "clv": 2.5,
      "edge_pct": 0.0,
      "odds": -110.0,
      "units": 5.0,
      "context_factors": "DATA_TOTAL v25.47 (Path 2) \u2014 CONTEXT_TOTAL: mkt=218.0 \u2192 ctx=215.56 | form=-0.2 (h:-4.1, a:+2.8) | h2h=-2.2 (n=5) | Market 218.0, Context 215.565 (disagreement=-2.44 \u2265 0.3). Bet UNDER 219.0 @ Fanatics -110. | Steam: no movement",
      "context_confirmed": 1,
      "model_spread": null,
      "closing_line": 216.5,
      "event_id": "0cab123e90bdf5d1d144a7e26ebc339c",
      "dt": "2026-04-26"
    },
    {
      "selection": "Kumar Rocker UNDER 2.5 EARNED RUNS",
      "sport": "baseball_mlb",
      "market_type": "PROP",
      "side_type": "PROP_UNDER",
      "result": "WIN",
      "pnl_units": 4.55,
      "clv": 0.0,
      "edge_pct": 21.35,
      "odds": -110.0,
      "units": 5.0,
      "context_factors": "",
      "context_confirmed": 0,
      "model_spread": null,
      "closing_line": 2.5,
      "event_id": "d8f901c0fc526d986a568d86c64039d5",
      "dt": "2026-04-26"
    },
    {
      "selection": "San Diego Padres@Arizona Diamondbacks OVER 15.0",
      "sport": "baseball_mlb",
      "market_type": "TOTAL",
      "side_type": "DATA_TOTAL",
      "result": "WIN",
      "pnl_units": 4.35,
      "clv": 0.0,
      "edge_pct": 0.0,
      "odds": -115.0,
      "units": 5.0,
      "context_factors": "DATA_TOTAL v25.47 (Path 2) \u2014 CONTEXT_TOTAL: mkt=15.0 \u2192 ctx=16.78 | form=+0.3 (h:+2.8, a:-0.7) | h2h=+0.1 (n=5) | pitcher=+0.8 (avg_era=5.12) | Market 15.0, Context 16.779 (disagreement=+1.78 \u2265 1.5). Bet OVER 15.0 @ Fanatics -115. | Steam: sharp opposes (-0.5)",
      "context_confirmed": 1,
      "model_spread": null,
      "closing_line": 15.0,
      "event_id": "02dcaedecc84abb3770b936306df02d9",
      "dt": "2026-04-26"
    },
    {
      "selection": "Reed Sheppard OVER 11.5 POINTS",
      "sport": "basketball_nba",
      "market_type": "PROP",
      "side_type": "PROP_BOOK_ARB",
      "result": "WIN",
      "pnl_units": 4.35,
      "clv": 0.0,
      "edge_pct": 15.0,
      "odds": -115.0,
      "units": 5.0,
      "context_factors": "PROP_BOOK_ARB \u2014 Sharp median 14.5 vs Caesars 11.5 (gap -3.0). Betting OVER at Caesars \u2014 easier number on sharp's side.",
      "context_confirmed": 1,
      "model_spread": null,
      "closing_line": 11.5,
      "event_id": "399d2e69e4408801d09e614c88779989",
      "dt": "2026-04-26"
    },
    {
      "selection": "Dino Prizmic +1.5",
      "sport": "tennis_atp_madrid_open",
      "market_type": "SPREAD",
      "side_type": "DOG",
      "result": "WIN",
      "pnl_units": 3.85,
      "clv": 0.0,
      "edge_pct": 13.94,
      "odds": -130.0,
      "units": 5.0,
      "context_factors": "P1 fatigue (-0.30) | P2 fatigue (+0.00) | CLV_MICRO_EDGE (edge=13.9%, pre_move=+1.50 TOWARD) | Steam: sharp confirms (+1.5)",
      "context_confirmed": 1,
      "model_spread": -0.8999999999999999,
      "closing_line": 1.5,
      "event_id": "ffa2c6e8aacbab297fe36b65b45c7e97",
      "dt": "2026-04-26"
    },
    {
      "selection": "Celta Vigo@Villarreal OVER 2.5",
      "sport": "soccer_spain_la_liga",
      "market_type": "TOTAL",
      "side_type": "OVER",
      "result": "WIN",
      "pnl_units": 3.85,
      "clv": 0.0,
      "edge_pct": 20.0,
      "odds": -130.0,
      "units": 5.0,
      "context_factors": "Away fast-paced (+0.3) | Steam: no movement",
      "context_confirmed": 1,
      "model_spread": -0.7000000000000001,
      "closing_line": 2.5,
      "event_id": "548f901ac0c811c39953f7e3769040cb",
      "dt": "2026-04-26"
    },
    {
      "selection": "Edmonton Oilers@Anaheim Ducks OVER 7.0",
      "sport": "icehockey_nhl",
      "market_type": "TOTAL",
      "side_type": "DATA_TOTAL",
      "result": "PUSH",
      "pnl_units": 0.0,
      "clv": 0.0,
      "edge_pct": 0.0,
      "odds": -110.0,
      "units": 5.0,
      "context_factors": "DATA_TOTAL v25.47 (Path 2) \u2014 CONTEXT_TOTAL: mkt=7.0 \u2192 ctx=8.0 | form=+0.3 (h:+1.5, a:+0.5) | h2h=+0.6 (n=5) | goalie=+1.4 (avg_sp=0.877) | Market 7.0, Context 8.0 (disagreement=+1.00 \u2265 1.0). Bet OVER 7.0 @ Caesars -110. | Steam: no movement",
      "context_confirmed": 1,
      "model_spread": null,
      "closing_line": 7.0,
      "event_id": "87206a7bb3286137bec3f9aef8d52f4d",
      "dt": "2026-04-26"
    },
    {
      "selection": "Como@Genoa OVER 2.5",
      "sport": "soccer_italy_serie_a",
      "market_type": "TOTAL",
      "side_type": "OVER",
      "result": "LOSS",
      "pnl_units": -5.0,
      "clv": 0.0,
      "edge_pct": 20.0,
      "odds": 102.0,
      "units": 5.0,
      "context_factors": "Away fast-paced (+0.4) | Steam: no movement",
      "context_confirmed": 1,
      "model_spread": 0.31,
      "closing_line": 2.5,
      "event_id": "b0d1e670b682b0ed37d6b0bc271efa6a",
      "dt": "2026-04-26",
      "actual_score": {
        "home": "Genoa",
        "away": "Como",
        "home_score": 0,
        "away_score": 2,
        "actual_total": 2,
        "actual_margin": -2
      }
    },
    {
      "selection": "Buffalo Sabres@Boston Bruins UNDER 6.0",
      "sport": "icehockey_nhl",
      "market_type": "TOTAL",
      "side_type": "UNDER",
      "result": "LOSS",
      "pnl_units": -5.0,
      "clv": 0.0,
      "edge_pct": 20.0,
      "odds": -115.0,
      "units": 5.0,
      "context_factors": "Division familiarity (-0.3) | Goalies: Jeremy Swayman 2.43 vs Alex Lyon 2.33 (-0.4) | Steam: no movement",
      "context_confirmed": 1,
      "model_spread": 0.08,
      "closing_line": 6.0,
      "event_id": "22d202aee787bcd6f4488f76fa15c3fd",
      "dt": "2026-04-26",
      "actual_score": {
        "home": "Boston Bruins",
        "away": "Buffalo Sabres",
        "home_score": 1,
        "away_score": 6,
        "actual_total": 7,
        "actual_margin": -5
      }
    },
    {
      "selection": "Colorado Avalanche@Los Angeles Kings UNDER 5.5",
      "sport": "icehockey_nhl",
      "market_type": "TOTAL",
      "side_type": "UNDER",
      "result": "LOSS",
      "pnl_units": -5.0,
      "clv": 0.0,
      "edge_pct": 20.0,
      "odds": 100.0,
      "units": 5.0,
      "context_factors": "Both teams slow-paced (-0.9) | Division familiarity (-0.3) | Goalies: Anton Forsberg 1.92 (recent 2.25) vs Scott Wedgewood 1.50 (recent 1.00) (-0.9) | Steam: no movement",
      "context_confirmed": 1,
      "model_spread": 0.73,
      "closing_line": 5.5,
      "event_id": "a8961751f4e2ecfa35e82df7de5f2269",
      "dt": "2026-04-26",
      "actual_score": {
        "home": "Los Angeles Kings",
        "away": "Colorado Avalanche",
        "home_score": 1,
        "away_score": 5,
        "actual_total": 6,
        "actual_margin": -4
      }
    },
    {
      "selection": "Cleveland Guardians@Toronto Blue Jays OVER 8.0",
      "sport": "baseball_mlb",
      "market_type": "TOTAL",
      "side_type": "OVER",
      "result": "LOSS",
      "pnl_units": -5.0,
      "clv": 0.5,
      "edge_pct": 20.0,
      "odds": -114.0,
      "units": 5.0,
      "context_factors": "Sunday game | Toronto Blue Jays SP: Patrick Corbin (3.39 ERA) | Cleveland Guardians SP: Slade Cecconi (7.22 ERA) | Pitching: Patrick Corbin 4.15 vs Slade Cecconi 4.59 (+0.3) | Park: Rogers Centre (+0.1) | Bullpen: Jays 4.33 vs Guardians 4.05 (+0.2) | Steam: no movement",
      "context_confirmed": 1,
      "model_spread": -0.7,
      "closing_line": 8.5,
      "event_id": "f98073ff54e69128fe75a3c5776fb520",
      "dt": "2026-04-26",
      "actual_score": {
        "home": "Toronto Blue Jays",
        "away": "Cleveland Guardians",
        "home_score": 4,
        "away_score": 2,
        "actual_total": 6,
        "actual_margin": 2
      }
    },
    {
      "selection": "Boston Celtics@Philadelphia 76ers UNDER 214.0",
      "sport": "basketball_nba",
      "market_type": "TOTAL",
      "side_type": "DATA_TOTAL",
      "result": "LOSS",
      "pnl_units": -5.0,
      "clv": 1.0,
      "edge_pct": 0.0,
      "odds": -110.0,
      "units": 5.0,
      "context_factors": "DATA_TOTAL v25.47 (Path 2) \u2014 CONTEXT_TOTAL: mkt=213.5 \u2192 ctx=207.23 | form=-2.4 (h:-15.4, a:-0.8) | h2h=-3.8 (n=5) | Market 213.5, Context 207.23 (disagreement=-6.27 \u2265 0.3). Bet UNDER 214.0 @ Fanatics -110. | Steam: no movement",
      "context_confirmed": 1,
      "model_spread": null,
      "closing_line": 213.0,
      "event_id": "62dc6619019d4366984883a71b283077",
      "dt": "2026-04-26",
      "actual_score": {
        "home": "Philadelphia 76ers",
        "away": "Boston Celtics",
        "home_score": 96,
        "away_score": 128,
        "actual_total": 224,
        "actual_margin": -32
      }
    },
    {
      "selection": "UTSA Roadrunners@Tulane Green Wave UNDER 13.5",
      "sport": "baseball_ncaa",
      "market_type": "TOTAL",
      "side_type": "UNDER",
      "result": "LOSS",
      "pnl_units": -5.0,
      "clv": 0.0,
      "edge_pct": 20.0,
      "odds": 100.0,
      "units": 5.0,
      "context_factors": "Sunday game | Tulane Green Wave allows 3.4 R/sunday | UTSA Roadrunners allows 6.2 R/sunday | Pitching edge: Tulane Green Wave (+0.8 pts) | Steam: no movement",
      "context_confirmed": 1,
      "model_spread": 0.96,
      "closing_line": 13.5,
      "event_id": "fab096b6f135afb07b5b8b7012730c49",
      "dt": "2026-04-26"
    },
    {
      "selection": "Nebraska Cornhuskers@Illinois Fighting Illini OVER 14.5",
      "sport": "baseball_ncaa",
      "market_type": "TOTAL",
      "side_type": "OVER",
      "result": "LOSS",
      "pnl_units": -5.0,
      "clv": 0.0,
      "edge_pct": 20.0,
      "odds": -111.0,
      "units": 5.0,
      "context_factors": "[SHADOW] Home fast-paced (+0.5) | Away fast-paced (+0.3) | Sunday game | Nebraska Cornhuskers SP: Cooper Katskee (4.50 ERA) | Illinois Fighting Illini allows 7.0 R/sunday | Nebraska Cornhuskers allows 4.6 R/sunday | Pitching edge: Nebraska Cornhuskers (-0.7 pts) | Steam: no movement",
      "context_confirmed": 1,
      "model_spread": 0.8,
      "closing_line": 14.5,
      "event_id": "81f61578c67ae2b3a87192f76af90934",
      "dt": "2026-04-26"
    }
  ],
  "season": {
    "result": "LOSS",
    "W": 250,
    "L": 200,
    "pnl": 74.9,
    "wagered": 2209.5
  },
  "by_sport": [
    {
      "sport": "baseball_mlb",
      "W": 38,
      "L": 33,
      "pnl": 15.9
    },
    {
      "sport": "baseball_ncaa",
      "W": 73,
      "L": 60,
      "pnl": 14.8
    },
    {
      "sport": "basketball_nba",
      "W": 48,
      "L": 47,
      "pnl": -23.0
    },
    {
      "sport": "basketball_ncaab",
      "W": 17,
      "L": 12,
      "pnl": 18.7
    },
    {
      "sport": "icehockey_nhl",
      "W": 58,
      "L": 37,
      "pnl": 36.4
    },
    {
      "sport": "soccer_germany_bundesliga",
      "W": 2,
      "L": 1,
      "pnl": 2.0
    },
    {
      "sport": "soccer_italy_serie_a",
      "W": 2,
      "L": 3,
      "pnl": -8.3
    },
    {
      "sport": "soccer_spain_la_liga",
      "W": 5,
      "L": 0,
      "pnl": 20.0
    },
    {
      "sport": "soccer_uefa_champs_league",
      "W": 0,
      "L": 1,
      "pnl": -5.0
    },
    {
      "sport": "soccer_usa_mls",
      "W": 0,
      "L": 1,
      "pnl": -4.5
    },
    {
      "sport": "TENNIS",
      "W": 7,
      "L": 5,
      "pnl": 7.9
    }
  ],
  "context_health": [
    {
      "factor": "Friday game",
      "W": 10,
      "L": 15,
      "pnl": -31.3,
      "first_half_pnl": -33.2,
      "second_half_pnl": 1.9,
      "trending": "BETTER"
    },
    {
      "factor": "Steam: no movement",
      "W": 20,
      "L": 24,
      "pnl": -29.9,
      "first_half_pnl": 3.0,
      "second_half_pnl": -33.0,
      "trending": "WORSE"
    },
    {
      "factor": "Home fast-paced",
      "W": 3,
      "L": 8,
      "pnl": -27.4,
      "first_half_pnl": -7.4,
      "second_half_pnl": -20.1,
      "trending": "WORSE"
    },
    {
      "factor": "Midweek game",
      "W": 17,
      "L": 18,
      "pnl": -20.0,
      "first_half_pnl": 6.0,
      "second_half_pnl": -26.0,
      "trending": "WORSE"
    },
    {
      "factor": "Park: Chase Field",
      "W": 1,
      "L": 3,
      "pnl": -10.4,
      "first_half_pnl": -0.5,
      "second_half_pnl": -10.0,
      "trending": "WORSE"
    },
    {
      "factor": "Away bounce-back",
      "W": 4,
      "L": 4,
      "pnl": -8.0,
      "first_half_pnl": -4.3,
      "second_half_pnl": -3.8,
      "trending": "STABLE"
    },
    {
      "factor": "Pitching edge: Clemson Tigers",
      "W": 1,
      "L": 2,
      "pnl": -7.2,
      "first_half_pnl": -5.0,
      "second_half_pnl": -2.2,
      "trending": "STABLE"
    },
    {
      "factor": "Pitching edge: TCU Horned Frogs",
      "W": 1,
      "L": 2,
      "pnl": -6.3,
      "first_half_pnl": 3.7,
      "second_half_pnl": -10.0,
      "trending": "WORSE"
    },
    {
      "factor": "Altitude",
      "W": 2,
      "L": 3,
      "pnl": -6.1,
      "first_half_pnl": 0.0,
      "second_half_pnl": -6.2,
      "trending": "WORSE"
    },
    {
      "factor": "Pitching edge: Wake Forest Demon Deacons",
      "W": 1,
      "L": 2,
      "pnl": -5.8,
      "first_half_pnl": -5.0,
      "second_half_pnl": -0.8,
      "trending": "BETTER"
    },
    {
      "factor": "Pitching edge: Nebraska Cornhuskers",
      "W": 1,
      "L": 2,
      "pnl": -5.7,
      "first_half_pnl": -5.0,
      "second_half_pnl": -0.7,
      "trending": "BETTER"
    },
    {
      "factor": "Weather: light rain, 11mph wind",
      "W": 1,
      "L": 2,
      "pnl": -5.7,
      "first_half_pnl": -5.0,
      "second_half_pnl": -0.7,
      "trending": "BETTER"
    },
    {
      "factor": "Home hot streak",
      "W": 1,
      "L": 2,
      "pnl": -5.4,
      "first_half_pnl": -4.5,
      "second_half_pnl": -0.9,
      "trending": "BETTER"
    },
    {
      "factor": "Both teams slow-paced",
      "W": 9,
      "L": 9,
      "pnl": -5.1,
      "first_half_pnl": 10.0,
      "second_half_pnl": -15.1,
      "trending": "WORSE"
    },
    {
      "factor": "Pitching edge: Tennessee Volunteers",
      "W": 1,
      "L": 2,
      "pnl": -5.0,
      "first_half_pnl": -5.0,
      "second_half_pnl": 0.0,
      "trending": "BETTER"
    },
    {
      "factor": "Away revenge game",
      "W": 5,
      "L": 5,
      "pnl": -4.4,
      "first_half_pnl": 2.1,
      "second_half_pnl": -6.5,
      "trending": "WORSE"
    },
    {
      "factor": "Steam: sharp opposes",
      "W": 9,
      "L": 8,
      "pnl": -2.4,
      "first_half_pnl": -3.5,
      "second_half_pnl": 1.1,
      "trending": "BETTER"
    },
    {
      "factor": "Pitching edge: Florida Gators",
      "W": 2,
      "L": 2,
      "pnl": -1.7,
      "first_half_pnl": -0.7,
      "second_half_pnl": -1.0,
      "trending": "STABLE"
    },
    {
      "factor": "Home 3-in-5",
      "W": 2,
      "L": 2,
      "pnl": -0.8,
      "first_half_pnl": -1.1,
      "second_half_pnl": 0.3,
      "trending": "STABLE"
    },
    {
      "factor": "Home bounce-back",
      "W": 5,
      "L": 4,
      "pnl": -0.4,
      "first_half_pnl": 5.5,
      "second_half_pnl": -5.9,
      "trending": "WORSE"
    },
    {
      "factor": "H2H high-scoring",
      "W": 2,
      "L": 2,
      "pnl": -0.2,
      "first_half_pnl": -10.0,
      "second_half_pnl": 9.8,
      "trending": "BETTER"
    },
    {
      "factor": "DATA_TOTAL v25.47",
      "W": 8,
      "L": 7,
      "pnl": 0.4,
      "first_half_pnl": -7.1,
      "second_half_pnl": 7.6,
      "trending": "BETTER"
    },
    {
      "factor": "Elo probability edge",
      "W": 8,
      "L": 7,
      "pnl": 1.1,
      "first_half_pnl": -7.6,
      "second_half_pnl": 8.7,
      "trending": "BETTER"
    },
    {
      "factor": "BLOCK_BACKTEST_TENNIS_APR24",
      "W": 2,
      "L": 1,
      "pnl": 2.9,
      "first_half_pnl": 3.2,
      "second_half_pnl": -0.3,
      "trending": "WORSE"
    },
    {
      "factor": "Indiana Hoosiers SP: Reagan Rivera",
      "W": 2,
      "L": 1,
      "pnl": 3.3,
      "first_half_pnl": 4.3,
      "second_half_pnl": -1.1,
      "trending": "WORSE"
    },
    {
      "factor": "Away 3-in-5",
      "W": 2,
      "L": 1,
      "pnl": 3.4,
      "first_half_pnl": 3.8,
      "second_half_pnl": -0.5,
      "trending": "WORSE"
    },
    {
      "factor": "Sunday game",
      "W": 18,
      "L": 15,
      "pnl": 3.4,
      "first_half_pnl": 12.9,
      "second_half_pnl": -9.5,
      "trending": "WORSE"
    },
    {
      "factor": "Pitching edge: Missouri Tigers",
      "W": 2,
      "L": 1,
      "pnl": 3.4,
      "first_half_pnl": 4.4,
      "second_half_pnl": -1.0,
      "trending": "WORSE"
    },
    {
      "factor": "Park: Kauffman Stadium",
      "W": 3,
      "L": 2,
      "pnl": 3.4,
      "first_half_pnl": -0.1,
      "second_half_pnl": 3.5,
      "trending": "BETTER"
    },
    {
      "factor": "Atlanta Braves SP: Bryce Elder",
      "W": 2,
      "L": 1,
      "pnl": 3.6,
      "first_half_pnl": -5.0,
      "second_half_pnl": 8.6,
      "trending": "BETTER"
    },
    {
      "factor": "Away fast-paced",
      "W": 21,
      "L": 17,
      "pnl": 3.7,
      "first_half_pnl": 34.2,
      "second_half_pnl": -30.5,
      "trending": "WORSE"
    },
    {
      "factor": "Pitching edge: California Golden Bears",
      "W": 2,
      "L": 1,
      "pnl": 3.7,
      "first_half_pnl": -5.0,
      "second_half_pnl": 8.7,
      "trending": "BETTER"
    },
    {
      "factor": "Pitching edge: Georgia Tech Yellow Jackets",
      "W": 2,
      "L": 1,
      "pnl": 3.8,
      "first_half_pnl": 4.3,
      "second_half_pnl": -0.6,
      "trending": "WORSE"
    },
    {
      "factor": "Away letdown spot",
      "W": 13,
      "L": 10,
      "pnl": 4.1,
      "first_half_pnl": 20.6,
      "second_half_pnl": -16.5,
      "trending": "WORSE"
    },
    {
      "factor": "Park: Great American Ball Park",
      "W": 2,
      "L": 1,
      "pnl": 4.3,
      "first_half_pnl": -5.0,
      "second_half_pnl": 9.3,
      "trending": "BETTER"
    },
    {
      "factor": "Park: Comerica Park",
      "W": 2,
      "L": 1,
      "pnl": 4.8,
      "first_half_pnl": 4.9,
      "second_half_pnl": -0.1,
      "trending": "WORSE"
    },
    {
      "factor": "Fri series-opener surcharge",
      "W": 2,
      "L": 1,
      "pnl": 5.0,
      "first_half_pnl": 5.0,
      "second_half_pnl": 0.0,
      "trending": "WORSE"
    },
    {
      "factor": "[SHADOW] Home fast-paced",
      "W": 11,
      "L": 8,
      "pnl": 8.4,
      "first_half_pnl": 2.1,
      "second_half_pnl": 6.3,
      "trending": "BETTER"
    },
    {
      "factor": "Home on B2B",
      "W": 5,
      "L": 2,
      "pnl": 8.5,
      "first_half_pnl": 3.9,
      "second_half_pnl": 4.7,
      "trending": "STABLE"
    },
    {
      "factor": "Division familiarity",
      "W": 17,
      "L": 12,
      "pnl": 8.5,
      "first_half_pnl": 17.9,
      "second_half_pnl": -9.4,
      "trending": "WORSE"
    },
    {
      "factor": "Detroit Tigers SP: Jack Flaherty",
      "W": 3,
      "L": 1,
      "pnl": 9.9,
      "first_half_pnl": -0.1,
      "second_half_pnl": 10.0,
      "trending": "BETTER"
    },
    {
      "factor": "Cross-country trip",
      "W": 7,
      "L": 3,
      "pnl": 10.7,
      "first_half_pnl": 9.6,
      "second_half_pnl": 1.1,
      "trending": "WORSE"
    },
    {
      "factor": "Ref: Francis Charron",
      "W": 3,
      "L": 0,
      "pnl": 10.9,
      "first_half_pnl": 3.9,
      "second_half_pnl": 7.1,
      "trending": "BETTER"
    },
    {
      "factor": "Pitching edge: Oregon Ducks",
      "W": 4,
      "L": 1,
      "pnl": 10.9,
      "first_half_pnl": 8.2,
      "second_half_pnl": 2.7,
      "trending": "WORSE"
    },
    {
      "factor": "Pitching edge: North Carolina Tar Heels",
      "W": 4,
      "L": 1,
      "pnl": 11.5,
      "first_half_pnl": 8.3,
      "second_half_pnl": 3.2,
      "trending": "WORSE"
    },
    {
      "factor": "Pitching edge: Houston Cougars",
      "W": 3,
      "L": 0,
      "pnl": 11.7,
      "first_half_pnl": 3.9,
      "second_half_pnl": 7.8,
      "trending": "BETTER"
    },
    {
      "factor": "H2H matchup",
      "W": 3,
      "L": 0,
      "pnl": 11.8,
      "first_half_pnl": 3.8,
      "second_half_pnl": 8.0,
      "trending": "BETTER"
    },
    {
      "factor": "Both teams fast-paced",
      "W": 7,
      "L": 3,
      "pnl": 12.5,
      "first_half_pnl": 10.6,
      "second_half_pnl": 1.9,
      "trending": "WORSE"
    },
    {
      "factor": "[SHADOW] Midweek game",
      "W": 11,
      "L": 7,
      "pnl": 12.5,
      "first_half_pnl": 2.5,
      "second_half_pnl": 10.0,
      "trending": "BETTER"
    },
    {
      "factor": "Home slow-paced",
      "W": 12,
      "L": 7,
      "pnl": 12.8,
      "first_half_pnl": 26.8,
      "second_half_pnl": -14.0,
      "trending": "WORSE"
    },
    {
      "factor": "Strong home team",
      "W": 3,
      "L": 0,
      "pnl": 13.7,
      "first_half_pnl": 4.3,
      "second_half_pnl": 9.3,
      "trending": "BETTER"
    },
    {
      "factor": "Kansas City Royals SP: Seth Lugo",
      "W": 3,
      "L": 0,
      "pnl": 13.9,
      "first_half_pnl": 4.9,
      "second_half_pnl": 9.0,
      "trending": "BETTER"
    },
    {
      "factor": "Home letdown spot",
      "W": 14,
      "L": 7,
      "pnl": 14.6,
      "first_half_pnl": 18.3,
      "second_half_pnl": -3.8,
      "trending": "WORSE"
    },
    {
      "factor": "Pitching edge: Miami Hurricanes",
      "W": 4,
      "L": 0,
      "pnl": 19.3,
      "first_half_pnl": 10.0,
      "second_half_pnl": 9.3,
      "trending": "STABLE"
    },
    {
      "factor": "Away on B2B",
      "W": 10,
      "L": 4,
      "pnl": 20.2,
      "first_half_pnl": 11.6,
      "second_half_pnl": 8.7,
      "trending": "STABLE"
    },
    {
      "factor": "Away slow-paced",
      "W": 24,
      "L": 13,
      "pnl": 36.7,
      "first_half_pnl": -8.1,
      "second_half_pnl": 44.8,
      "trending": "BETTER"
    },
    {
      "factor": "Saturday game",
      "W": 29,
      "L": 17,
      "pnl": 40.8,
      "first_half_pnl": 34.3,
      "second_half_pnl": 6.5,
      "trending": "WORSE"
    }
  ],
  "day_of_week": [
    {
      "day_of_week": "Friday",
      "sport": "baseball_ncaa",
      "W": 10,
      "L": 15,
      "pnl": -32.0
    },
    {
      "day_of_week": "Wednesday",
      "sport": "basketball_nba",
      "W": 3,
      "L": 7,
      "pnl": -19.3
    },
    {
      "day_of_week": "Saturday",
      "sport": "icehockey_nhl",
      "W": 9,
      "L": 11,
      "pnl": -17.3
    },
    {
      "day_of_week": "Wednesday",
      "sport": "baseball_mlb",
      "W": 5,
      "L": 8,
      "pnl": -16.1
    },
    {
      "day_of_week": "Saturday",
      "sport": "basketball_nba",
      "W": 7,
      "L": 9,
      "pnl": -14.9
    },
    {
      "day_of_week": "Thursday",
      "sport": "baseball_ncaa",
      "W": 5,
      "L": 6,
      "pnl": -11.6
    },
    {
      "day_of_week": "Monday",
      "sport": "baseball_ncaa",
      "W": 1,
      "L": 3,
      "pnl": -10.6
    },
    {
      "day_of_week": "Monday",
      "sport": "baseball_mlb",
      "W": 3,
      "L": 5,
      "pnl": -10.5
    },
    {
      "day_of_week": "Saturday",
      "sport": "soccer_italy_serie_a",
      "W": 0,
      "L": 2,
      "pnl": -10.0
    },
    {
      "day_of_week": "Thursday",
      "sport": "baseball_mlb",
      "W": 4,
      "L": 5,
      "pnl": -7.6
    },
    {
      "day_of_week": "Sunday",
      "sport": "tennis_atp_monte_carlo_masters",
      "W": 1,
      "L": 2,
      "pnl": -6.7
    },
    {
      "day_of_week": "Wednesday",
      "sport": "baseball_ncaa",
      "W": 1,
      "L": 2,
      "pnl": -5.6
    },
    {
      "day_of_week": "Thursday",
      "sport": "basketball_nba",
      "W": 6,
      "L": 6,
      "pnl": -4.9
    },
    {
      "day_of_week": "Sunday",
      "sport": "soccer_italy_serie_a",
      "W": 1,
      "L": 1,
      "pnl": -1.8
    },
    {
      "day_of_week": "Sunday",
      "sport": "icehockey_nhl",
      "W": 11,
      "L": 8,
      "pnl": -1.7
    },
    {
      "day_of_week": "Sunday",
      "sport": "baseball_ncaa",
      "W": 14,
      "L": 13,
      "pnl": -1.5
    },
    {
      "day_of_week": "Saturday",
      "sport": "basketball_ncaab",
      "W": 2,
      "L": 2,
      "pnl": -1.3
    },
    {
      "day_of_week": "Monday",
      "sport": "basketball_nba",
      "W": 12,
      "L": 11,
      "pnl": -1.2
    },
    {
      "day_of_week": "",
      "sport": "basketball_nba",
      "W": 1,
      "L": 1,
      "pnl": -0.5
    },
    {
      "day_of_week": "Saturday",
      "sport": "soccer_germany_bundesliga",
      "W": 1,
      "L": 1,
      "pnl": -0.2
    },
    {
      "day_of_week": "Friday",
      "sport": "icehockey_nhl",
      "W": 3,
      "L": 2,
      "pnl": 1.6
    },
    {
      "day_of_week": "Monday",
      "sport": "icehockey_nhl",
      "W": 4,
      "L": 3,
      "pnl": 2.2
    },
    {
      "day_of_week": "Sunday",
      "sport": "basketball_nba",
      "W": 5,
      "L": 4,
      "pnl": 2.6
    },
    {
      "day_of_week": "Friday",
      "sport": "basketball_ncaab",
      "W": 4,
      "L": 3,
      "pnl": 2.8
    },
    {
      "day_of_week": "Wednesday",
      "sport": "basketball_ncaab",
      "W": 5,
      "L": 4,
      "pnl": 2.8
    },
    {
      "day_of_week": "Thursday",
      "sport": "basketball_ncaab",
      "W": 2,
      "L": 1,
      "pnl": 4.7
    },
    {
      "day_of_week": "Friday",
      "sport": "baseball_mlb",
      "W": 4,
      "L": 3,
      "pnl": 5.3
    },
    {
      "day_of_week": "Friday",
      "sport": "basketball_nba",
      "W": 11,
      "L": 8,
      "pnl": 5.8
    },
    {
      "day_of_week": "",
      "sport": "tennis_atp_madrid_open",
      "W": 2,
      "L": 0,
      "pnl": 6.4
    },
    {
      "day_of_week": "Sunday",
      "sport": "basketball_ncaab",
      "W": 3,
      "L": 1,
      "pnl": 7.7
    },
    {
      "day_of_week": "Saturday",
      "sport": "soccer_spain_la_liga",
      "W": 2,
      "L": 0,
      "pnl": 8.9
    },
    {
      "day_of_week": null,
      "sport": "baseball_ncaa",
      "W": 2,
      "L": 0,
      "pnl": 9.2
    },
    {
      "day_of_week": "Tuesday",
      "sport": "basketball_nba",
      "W": 3,
      "L": 1,
      "pnl": 9.2
    },
    {
      "day_of_week": "Wednesday",
      "sport": "icehockey_nhl",
      "W": 6,
      "L": 2,
      "pnl": 10.9
    },
    {
      "day_of_week": "Sunday",
      "sport": "baseball_mlb",
      "W": 7,
      "L": 4,
      "pnl": 11.9
    },
    {
      "day_of_week": "Tuesday",
      "sport": "baseball_mlb",
      "W": 6,
      "L": 4,
      "pnl": 12.4
    },
    {
      "day_of_week": "Tuesday",
      "sport": "baseball_ncaa",
      "W": 12,
      "L": 7,
      "pnl": 15.1
    },
    {
      "day_of_week": "Tuesday",
      "sport": "icehockey_nhl",
      "W": 8,
      "L": 3,
      "pnl": 18.1
    },
    {
      "day_of_week": "Saturday",
      "sport": "baseball_mlb",
      "W": 9,
      "L": 4,
      "pnl": 20.4
    },
    {
      "day_of_week": "Thursday",
      "sport": "icehockey_nhl",
      "W": 17,
      "L": 8,
      "pnl": 22.6
    },
    {
      "day_of_week": "Saturday",
      "sport": "baseball_ncaa",
      "W": 28,
      "L": 14,
      "pnl": 51.8
    }
  ],
  "edge_cap": [
    {
      "bucket": "AT_CAP",
      "W": 171,
      "L": 141,
      "pnl": 55.3,
      "avg_clv": 0.2
    },
    {
      "bucket": "BELOW_CAP",
      "W": 79,
      "L": 59,
      "pnl": 19.5,
      "avg_clv": 0.6
    }
  ],
  "concentration_risk": [
    {
      "dt": "2026-03-23",
      "sport": "basketball_nba",
      "side_type": "PROP_OVER",
      "cnt": 16,
      "total_units": 80.0
    },
    {
      "dt": "2026-03-28",
      "sport": "baseball_ncaa",
      "side_type": "UNDER",
      "cnt": 8,
      "total_units": 40.0
    },
    {
      "dt": "2026-03-22",
      "sport": "baseball_ncaa",
      "side_type": "UNDER",
      "cnt": 7,
      "total_units": 35.0
    },
    {
      "dt": "2026-03-29",
      "sport": "baseball_ncaa",
      "side_type": "UNDER",
      "cnt": 7,
      "total_units": 35.0
    },
    {
      "dt": "2026-03-04",
      "sport": "basketball_ncaab",
      "side_type": "DOG",
      "cnt": 6,
      "total_units": 29.0
    },
    {
      "dt": "2026-03-14",
      "sport": "baseball_ncaa",
      "side_type": "DOG",
      "cnt": 6,
      "total_units": 24.0
    },
    {
      "dt": "2026-04-02",
      "sport": "baseball_ncaa",
      "side_type": "OVER",
      "cnt": 6,
      "total_units": 30.0
    },
    {
      "dt": "2026-03-04",
      "sport": "baseball_ncaa",
      "side_type": "DOG",
      "cnt": 5,
      "total_units": 19.5
    },
    {
      "dt": "2026-03-06",
      "sport": "basketball_ncaab",
      "side_type": "DOG",
      "cnt": 5,
      "total_units": 23.5
    },
    {
      "dt": "2026-03-19",
      "sport": "icehockey_nhl",
      "side_type": "DOG",
      "cnt": 5,
      "total_units": 21.5
    }
  ],
  "over_under": [
    {
      "sport": "baseball_mlb",
      "side_type": "OVER",
      "W": 14,
      "L": 13,
      "pnl": -2.5
    },
    {
      "sport": "baseball_mlb",
      "side_type": "UNDER",
      "W": 10,
      "L": 8,
      "pnl": 4.3
    },
    {
      "sport": "baseball_ncaa",
      "side_type": "OVER",
      "W": 26,
      "L": 24,
      "pnl": -10.5
    },
    {
      "sport": "baseball_ncaa",
      "side_type": "UNDER",
      "W": 37,
      "L": 30,
      "pnl": 7.2
    },
    {
      "sport": "basketball_nba",
      "side_type": "OVER",
      "W": 1,
      "L": 1,
      "pnl": -0.5
    },
    {
      "sport": "basketball_nba",
      "side_type": "UNDER",
      "W": 4,
      "L": 6,
      "pnl": -11.8
    },
    {
      "sport": "basketball_ncaab",
      "side_type": "UNDER",
      "W": 0,
      "L": 1,
      "pnl": -5.0
    },
    {
      "sport": "icehockey_nhl",
      "side_type": "OVER",
      "W": 11,
      "L": 8,
      "pnl": 2.3
    },
    {
      "sport": "icehockey_nhl",
      "side_type": "UNDER",
      "W": 20,
      "L": 16,
      "pnl": 0.7
    },
    {
      "sport": "soccer_germany_bundesliga",
      "side_type": "OVER",
      "W": 2,
      "L": 0,
      "pnl": 7.0
    },
    {
      "sport": "soccer_germany_bundesliga",
      "side_type": "UNDER",
      "W": 0,
      "L": 1,
      "pnl": -5.0
    },
    {
      "sport": "soccer_italy_serie_a",
      "side_type": "OVER",
      "W": 1,
      "L": 2,
      "pnl": -6.5
    },
    {
      "sport": "soccer_italy_serie_a",
      "side_type": "UNDER",
      "W": 1,
      "L": 1,
      "pnl": -1.8
    },
    {
      "sport": "soccer_spain_la_liga",
      "side_type": "OVER",
      "W": 3,
      "L": 0,
      "pnl": 12.8
    },
    {
      "sport": "soccer_spain_la_liga",
      "side_type": "UNDER",
      "W": 1,
      "L": 0,
      "pnl": 3.6
    },
    {
      "sport": "soccer_uefa_champs_league",
      "side_type": "OVER",
      "W": 0,
      "L": 1,
      "pnl": -5.0
    },
    {
      "sport": "soccer_usa_mls",
      "side_type": "OVER",
      "W": 0,
      "L": 1,
      "pnl": -4.5
    }
  ],
  "ungraded": [],
  "last_10": [
    "WIN",
    "WIN",
    "LOSS",
    "LOSS",
    "WIN",
    "WIN",
    "WIN",
    "WIN",
    "LOSS",
    "WIN"
  ],
  "streak": 2,
  "streak_type": "WIN",
  "shadow_blocked_picks": [
    {
      "created_at": "2026-04-27T00:03:46.630517+00:00",
      "sport": "basketball_nba",
      "event_id": "399d2e69e4408801d09e614c88779989",
      "selection": "Dorian Finney-Smith OVER 1.5 pts",
      "market_type": "PROP",
      "line": 1.5,
      "odds": null,
      "edge_pct": null,
      "units": null,
      "reason": "PROP_PLAYOFF_ROLE_GATE_SHADOW (v25.90, pts_avg=3.8 < 12.0, stat=pts, line=1.5)"
    },
    {
      "created_at": "2026-04-27T00:03:44.492835+00:00",
      "sport": "basketball_nba",
      "event_id": "399d2e69e4408801d09e614c88779989",
      "selection": "Josh Okogie OVER 2.5 pts",
      "market_type": "PROP",
      "line": 2.5,
      "odds": null,
      "edge_pct": null,
      "units": null,
      "reason": "PROP_PLAYOFF_ROLE_GATE_SHADOW (v25.90, pts_avg=3.6 < 12.0, stat=pts, line=2.5)"
    },
    {
      "created_at": "2026-04-27T00:03:44.268808+00:00",
      "sport": "basketball_nba",
      "event_id": "399d2e69e4408801d09e614c88779989",
      "selection": "Aaron Holiday OVER 2.5 pts",
      "market_type": "PROP",
      "line": 2.5,
      "odds": null,
      "edge_pct": null,
      "units": null,
      "reason": "PROP_PLAYOFF_ROLE_GATE_SHADOW (v25.90, pts_avg=4.1 < 12.0, stat=pts, line=2.5)"
    },
    {
      "created_at": "2026-04-27T00:03:42.492782+00:00",
      "sport": "basketball_nba",
      "event_id": "399d2e69e4408801d09e614c88779989",
      "selection": "Bronny James OVER 1.5 pts",
      "market_type": "PROP",
      "line": 1.5,
      "odds": null,
      "edge_pct": null,
      "units": null,
      "reason": "PROP_PLAYOFF_ROLE_GATE_SHADOW (v25.90, pts_avg=4.2 < 12.0, stat=pts, line=1.5)"
    },
    {
      "created_at": "2026-04-27T00:03:32.989768+00:00",
      "sport": "basketball_nba",
      "event_id": "399d2e69e4408801d09e614c88779989",
      "selection": "Marcus Smart OVER 2.5 reb",
      "market_type": "PROP",
      "line": 2.5,
      "odds": null,
      "edge_pct": null,
      "units": null,
      "reason": "PROP_PLAYOFF_ROLE_GATE_SHADOW (v25.90, pts_avg=11.5 < 12.0, stat=reb, line=2.5)"
    },
    {
      "created_at": "2026-04-27T00:03:31.247076+00:00",
      "sport": "basketball_nba",
      "event_id": "399d2e69e4408801d09e614c88779989",
      "selection": "Jaxson Hayes OVER 3.5 reb",
      "market_type": "PROP",
      "line": 3.5,
      "odds": null,
      "edge_pct": null,
      "units": null,
      "reason": "PROP_PLAYOFF_ROLE_GATE_SHADOW (v25.90, pts_avg=9.7 < 12.0, stat=reb, line=3.5)"
    },
    {
      "created_at": "2026-04-27T00:03:31.016357+00:00",
      "sport": "basketball_nba",
      "event_id": "399d2e69e4408801d09e614c88779989",
      "selection": "Luke Kennard OVER 4.5 reb",
      "market_type": "PROP",
      "line": 4.5,
      "odds": null,
      "edge_pct": null,
      "units": null,
      "reason": "PROP_PLAYOFF_ROLE_GATE_SHADOW (v25.90, pts_avg=11.9 < 12.0, stat=reb, line=4.5)"
    },
    {
      "created_at": "2026-04-27T00:03:30.785605+00:00",
      "sport": "basketball_nba",
      "event_id": "399d2e69e4408801d09e614c88779989",
      "selection": "Tari Eason OVER 7.5 reb",
      "market_type": "PROP",
      "line": 7.5,
      "odds": null,
      "edge_pct": null,
      "units": null,
      "reason": "PROP_PLAYOFF_ROLE_GATE_SHADOW (v25.90, pts_avg=10.2 < 12.0, stat=reb, line=7.5)"
    },
    {
      "created_at": "2026-04-27T00:03:30.187767+00:00",
      "sport": "basketball_nba",
      "event_id": "399d2e69e4408801d09e614c88779989",
      "selection": "Deandre Ayton UNDER 8.5 reb",
      "market_type": "PROP",
      "line": 8.5,
      "odds": -132.0,
      "edge_pct": null,
      "units": null,
      "reason": "PROP_DIVERGENCE_GATE (proj=6.5 vs market_median=8.5, gap=2.0 > thr 1.5, books=4)"
    },
    {
      "created_at": "2026-04-27T00:03:30.187218+00:00",
      "sport": "basketball_nba",
      "event_id": "399d2e69e4408801d09e614c88779989",
      "selection": "Deandre Ayton UNDER 8.5 reb",
      "market_type": "PROP",
      "line": 8.5,
      "odds": -140.0,
      "edge_pct": null,
      "units": null,
      "reason": "PROP_DIVERGENCE_GATE (proj=6.5 vs market_median=8.5, gap=2.0 > thr 1.5, books=4)"
    },
    {
      "created_at": "2026-04-27T00:03:30.186708+00:00",
      "sport": "basketball_nba",
      "event_id": "399d2e69e4408801d09e614c88779989",
      "selection": "Deandre Ayton UNDER 8.5 reb",
      "market_type": "PROP",
      "line": 8.5,
      "odds": -139.0,
      "edge_pct": null,
      "units": null,
      "reason": "PROP_DIVERGENCE_GATE (proj=6.5 vs market_median=8.5, gap=2.0 > thr 1.5, books=4)"
    },
    {
      "created_at": "2026-04-27T00:03:30.185969+00:00",
      "sport": "basketball_nba",
      "event_id": "399d2e69e4408801d09e614c88779989",
      "selection": "Deandre Ayton UNDER 8.5 reb",
      "market_type": "PROP",
      "line": 8.5,
      "odds": -123.0,
      "edge_pct": null,
      "units": null,
      "reason": "PROP_DIVERGENCE_GATE (proj=6.5 vs market_median=8.5, gap=2.0 > thr 1.5, books=4)"
    },
    {
      "created_at": "2026-04-27T00:03:30.070827+00:00",
      "sport": "basketball_nba",
      "event_id": "399d2e69e4408801d09e614c88779989",
      "selection": "Deandre Ayton OVER 8.5 reb",
      "market_type": "PROP",
      "line": 8.5,
      "odds": null,
      "edge_pct": null,
      "units": null,
      "reason": "PROP_PLAYOFF_ROLE_GATE_SHADOW (v25.90, pts_avg=11.9 < 12.0, stat=reb, line=8.5)"
    },
    {
      "created_at": "2026-04-27T00:03:28.614486+00:00",
      "sport": "basketball_nba",
      "event_id": "399d2e69e4408801d09e614c88779989",
      "selection": "Jaxson Hayes OVER 6.5 pts",
      "market_type": "PROP",
      "line": 6.5,
      "odds": null,
      "edge_pct": null,
      "units": null,
      "reason": "PROP_PLAYOFF_ROLE_GATE_SHADOW (v25.90, pts_avg=9.7 < 12.0, stat=pts, line=6.5)"
    },
    {
      "created_at": "2026-04-27T00:03:28.382489+00:00",
      "sport": "basketball_nba",
      "event_id": "399d2e69e4408801d09e614c88779989",
      "selection": "Deandre Ayton OVER 10.5 pts",
      "market_type": "PROP",
      "line": 10.5,
      "odds": null,
      "edge_pct": null,
      "units": null,
      "reason": "PROP_PLAYOFF_ROLE_GATE_SHADOW (v25.90, pts_avg=11.9 < 12.0, stat=pts, line=10.5)"
    },
    {
      "created_at": "2026-04-27T00:03:28.167623+00:00",
      "sport": "basketball_nba",
      "event_id": "399d2e69e4408801d09e614c88779989",
      "selection": "Marcus Smart OVER 11.5 pts",
      "market_type": "PROP",
      "line": 11.5,
      "odds": null,
      "edge_pct": null,
      "units": null,
      "reason": "PROP_PLAYOFF_ROLE_GATE_SHADOW (v25.90, pts_avg=11.5 < 12.0, stat=pts, line=11.5)"
    },
    {
      "created_at": "2026-04-27T00:03:27.942529+00:00",
      "sport": "basketball_nba",
      "event_id": "399d2e69e4408801d09e614c88779989",
      "selection": "Luke Kennard OVER 12.5 pts",
      "market_type": "PROP",
      "line": 12.5,
      "odds": null,
      "edge_pct": null,
      "units": null,
      "reason": "PROP_PLAYOFF_ROLE_GATE_SHADOW (v25.90, pts_avg=11.9 < 12.0, stat=pts, line=12.5)"
    },
    {
      "created_at": "2026-04-27T00:03:27.618219+00:00",
      "sport": "basketball_nba",
      "event_id": "399d2e69e4408801d09e614c88779989",
      "selection": "Tari Eason UNDER 13.5 pts",
      "market_type": "PROP",
      "line": 13.5,
      "odds": -125.0,
      "edge_pct": null,
      "units": null,
      "reason": "PROP_DIVERGENCE_GATE (proj=10.1 vs market_median=13.5, gap=3.4 > thr 3.0, books=4)"
    },
    {
      "created_at": "2026-04-27T00:03:27.508954+00:00",
      "sport": "basketball_nba",
      "event_id": "399d2e69e4408801d09e614c88779989",
      "selection": "Tari Eason OVER 13.5 pts",
      "market_type": "PROP",
      "line": 13.5,
      "odds": null,
      "edge_pct": null,
      "units": null,
      "reason": "PROP_PLAYOFF_ROLE_GATE_SHADOW (v25.90, pts_avg=10.2 < 12.0, stat=pts, line=13.5)"
    },
    {
      "created_at": "2026-04-27T00:03:27.248476+00:00",
      "sport": "basketball_nba",
      "event_id": "399d2e69e4408801d09e614c88779989",
      "selection": "Austin Reaves OVER 15.5 pts",
      "market_type": "PROP",
      "line": 15.5,
      "odds": -127.0,
      "edge_pct": null,
      "units": null,
      "reason": "PROP_DIVERGENCE_GATE (proj=20.6 vs market_median=15.5, gap=5.1 > thr 3.0, books=3)"
    },
    {
      "created_at": "2026-04-27T00:03:27.247969+00:00",
      "sport": "basketball_nba",
      "event_id": "399d2e69e4408801d09e614c88779989",
      "selection": "Austin Reaves OVER 15.5 pts",
      "market_type": "PROP",
      "line": 15.5,
      "odds": -111.0,
      "edge_pct": null,
      "units": null,
      "reason": "PROP_DIVERGENCE_GATE (proj=20.6 vs market_median=15.5, gap=5.1 > thr 3.0, books=3)"
    },
    {
      "created_at": "2026-04-27T00:03:27.127474+00:00",
      "sport": "basketball_nba",
      "event_id": "399d2e69e4408801d09e614c88779989",
      "selection": "Reed Sheppard UNDER 17.5 pts",
      "market_type": "PROP",
      "line": 17.5,
      "odds": -110.0,
      "edge_pct": null,
      "units": null,
      "reason": "PROP_DIVERGENCE_GATE (proj=12.9 vs market_median=17.5, gap=4.6 > thr 3.0, books=4)"
    },
    {
      "created_at": "2026-04-27T00:03:27.126399+00:00",
      "sport": "basketball_nba",
      "event_id": "399d2e69e4408801d09e614c88779989",
      "selection": "Reed Sheppard UNDER 17.5 pts",
      "market_type": "PROP",
      "line": 17.5,
      "odds": -115.0,
      "edge_pct": null,
      "units": null,
      "reason": "PROP_DIVERGENCE_GATE (proj=12.9 vs market_median=17.5, gap=4.6 > thr 3.0, books=4)"
    },
    {
      "created_at": "2026-04-27T00:03:25.795267+00:00",
      "sport": "basketball_nba",
      "event_id": "399d2e69e4408801d09e614c88779989",
      "selection": "Deandre Ayton OVER 0.5 ast",
      "market_type": "PROP",
      "line": 0.5,
      "odds": null,
      "edge_pct": null,
      "units": null,
      "reason": "PROP_PLAYOFF_ROLE_GATE_SHADOW (v25.90, pts_avg=11.9 < 12.0, stat=ast, line=0.5)"
    },
    {
      "created_at": "2026-04-27T00:03:24.022497+00:00",
      "sport": "basketball_nba",
      "event_id": "399d2e69e4408801d09e614c88779989",
      "selection": "Luke Kennard OVER 2.5 ast",
      "market_type": "PROP",
      "line": 2.5,
      "odds": null,
      "edge_pct": null,
      "units": null,
      "reason": "PROP_PLAYOFF_ROLE_GATE_SHADOW (v25.90, pts_avg=11.9 < 12.0, stat=ast, line=2.5)"
    },
    {
      "created_at": "2026-04-27T00:03:20.749833+00:00",
      "sport": "basketball_nba",
      "event_id": "399d2e69e4408801d09e614c88779989",
      "selection": "Marcus Smart OVER 4.5 ast",
      "market_type": "PROP",
      "line": 4.5,
      "odds": null,
      "edge_pct": null,
      "units": null,
      "reason": "PROP_PLAYOFF_ROLE_GATE_SHADOW (v25.90, pts_avg=11.5 < 12.0, stat=ast, line=4.5)"
    },
    {
      "created_at": "2026-04-26T23:03:56.215361+00:00",
      "sport": "basketball_nba",
      "event_id": "399d2e69e4408801d09e614c88779989",
      "selection": "Josh Okogie OVER 2.5 pts",
      "market_type": "PROP",
      "line": 2.5,
      "odds": null,
      "edge_pct": null,
      "units": null,
      "reason": "PROP_PLAYOFF_ROLE_GATE_SHADOW (v25.90, pts_avg=3.6 < 12.0, stat=pts, line=2.5)"
    },
    {
      "created_at": "2026-04-26T23:03:55.958374+00:00",
      "sport": "basketball_nba",
      "event_id": "399d2e69e4408801d09e614c88779989",
      "selection": "Bronny James OVER 1.5 pts",
      "market_type": "PROP",
      "line": 1.5,
      "odds": null,
      "edge_pct": null,
      "units": null,
      "reason": "PROP_PLAYOFF_ROLE_GATE_SHADOW (v25.90, pts_avg=4.2 < 12.0, stat=pts, line=1.5)"
    },
    {
      "created_at": "2026-04-26T23:03:52.891379+00:00",
      "sport": "basketball_nba",
      "event_id": "399d2e69e4408801d09e614c88779989",
      "selection": "Marcus Smart OVER 2.5 reb",
      "market_type": "PROP",
      "line": 2.5,
      "odds": null,
      "edge_pct": null,
      "units": null,
      "reason": "PROP_PLAYOFF_ROLE_GATE_SHADOW (v25.90, pts_avg=11.5 < 12.0, stat=reb, line=2.5)"
    },
    {
      "created_at": "2026-04-26T23:03:52.354574+00:00",
      "sport": "basketball_nba",
      "event_id": "399d2e69e4408801d09e614c88779989",
      "selection": "Jaxson Hayes OVER 3.5 reb",
      "market_type": "PROP",
      "line": 3.5,
      "odds": null,
      "edge_pct": null,
      "units": null,
      "reason": "PROP_PLAYOFF_ROLE_GATE_SHADOW (v25.90, pts_avg=9.7 < 12.0, stat=reb, line=3.5)"
    },
    {
      "created_at": "2026-04-26T23:03:52.072547+00:00",
      "sport": "basketball_nba",
      "event_id": "399d2e69e4408801d09e614c88779989",
      "selection": "Luke Kennard OVER 4.5 reb",
      "market_type": "PROP",
      "line": 4.5,
      "odds": null,
      "edge_pct": null,
      "units": null,
      "reason": "PROP_PLAYOFF_ROLE_GATE_SHADOW (v25.90, pts_avg=11.9 < 12.0, stat=reb, line=4.5)"
    },
    {
      "created_at": "2026-04-26T23:03:51.775903+00:00",
      "sport": "basketball_nba",
      "event_id": "399d2e69e4408801d09e614c88779989",
      "selection": "Tari Eason OVER 7.5 reb",
      "market_type": "PROP",
      "line": 7.5,
      "odds": null,
      "edge_pct": null,
      "units": null,
      "reason": "PROP_PLAYOFF_ROLE_GATE_SHADOW (v25.90, pts_avg=10.2 < 12.0, stat=reb, line=7.5)"
    },
    {
      "created_at": "2026-04-26T23:03:50.689294+00:00",
      "sport": "basketball_nba",
      "event_id": "399d2e69e4408801d09e614c88779989",
      "selection": "Jaxson Hayes OVER 6.5 pts",
      "market_type": "PROP",
      "line": 6.5,
      "odds": null,
      "edge_pct": null,
      "units": null,
      "reason": "PROP_PLAYOFF_ROLE_GATE_SHADOW (v25.90, pts_avg=9.7 < 12.0, stat=pts, line=6.5)"
    },
    {
      "created_at": "2026-04-26T23:03:50.409918+00:00",
      "sport": "basketball_nba",
      "event_id": "399d2e69e4408801d09e614c88779989",
      "selection": "Marcus Smart OVER 11.5 pts",
      "market_type": "PROP",
      "line": 11.5,
      "odds": null,
      "edge_pct": null,
      "units": null,
      "reason": "PROP_PLAYOFF_ROLE_GATE_SHADOW (v25.90, pts_avg=11.5 < 12.0, stat=pts, line=11.5)"
    },
    {
      "created_at": "2026-04-26T23:03:50.127150+00:00",
      "sport": "basketball_nba",
      "event_id": "399d2e69e4408801d09e614c88779989",
      "selection": "Luke Kennard OVER 12.5 pts",
      "market_type": "PROP",
      "line": 12.5,
      "odds": null,
      "edge_pct": null,
      "units": null,
      "reason": "PROP_PLAYOFF_ROLE_GATE_SHADOW (v25.90, pts_avg=11.9 < 12.0, stat=pts, line=12.5)"
    },
    {
      "created_at": "2026-04-26T23:03:49.701908+00:00",
      "sport": "basketball_nba",
      "event_id": "399d2e69e4408801d09e614c88779989",
      "selection": "Tari Eason UNDER 13.5 pts",
      "market_type": "PROP",
      "line": 13.5,
      "odds": -125.0,
      "edge_pct": null,
      "units": null,
      "reason": "PROP_DIVERGENCE_GATE (proj=10.1 vs market_median=13.5, gap=3.4 > thr 3.0, books=4)"
    },
    {
      "created_at": "2026-04-26T23:03:49.559738+00:00",
      "sport": "basketball_nba",
      "event_id": "399d2e69e4408801d09e614c88779989",
      "selection": "Tari Eason OVER 13.5 pts",
      "market_type": "PROP",
      "line": 13.5,
      "odds": null,
      "edge_pct": null,
      "units": null,
      "reason": "PROP_PLAYOFF_ROLE_GATE_SHADOW (v25.90, pts_avg=10.2 < 12.0, stat=pts, line=13.5)"
    },
    {
      "created_at": "2026-04-26T23:03:48.201674+00:00",
      "sport": "basketball_nba",
      "event_id": "399d2e69e4408801d09e614c88779989",
      "selection": "Luke Kennard OVER 2.5 ast",
      "market_type": "PROP",
      "line": 2.5,
      "odds": null,
      "edge_pct": null,
      "units": null,
      "reason": "PROP_PLAYOFF_ROLE_GATE_SHADOW (v25.90, pts_avg=11.9 < 12.0, stat=ast, line=2.5)"
    },
    {
      "created_at": "2026-04-26T23:03:47.931107+00:00",
      "sport": "basketball_nba",
      "event_id": "399d2e69e4408801d09e614c88779989",
      "selection": "Marcus Smart OVER 4.5 ast",
      "market_type": "PROP",
      "line": 4.5,
      "odds": null,
      "edge_pct": null,
      "units": null,
      "reason": "PROP_PLAYOFF_ROLE_GATE_SHADOW (v25.90, pts_avg=11.5 < 12.0, stat=ast, line=4.5)"
    },
    {
      "created_at": "2026-04-26T23:03:42.220664+00:00",
      "sport": "basketball_nba",
      "event_id": "62dc6619019d4366984883a71b283077",
      "selection": "Quentin Grimes OVER 1.5 reb",
      "market_type": "PROP",
      "line": 1.5,
      "odds": null,
      "edge_pct": null,
      "units": null,
      "reason": "PROP_PLAYOFF_ROLE_GATE_SHADOW (v25.90, pts_avg=10.6 < 12.0, stat=reb, line=1.5)"
    },
    {
      "created_at": "2026-04-26T23:03:41.872501+00:00",
      "sport": "basketball_nba",
      "event_id": "62dc6619019d4366984883a71b283077",
      "selection": "Quentin Grimes OVER 1.5 ast",
      "market_type": "PROP",
      "line": 1.5,
      "odds": null,
      "edge_pct": null,
      "units": null,
      "reason": "PROP_PLAYOFF_ROLE_GATE_SHADOW (v25.90, pts_avg=10.6 < 12.0, stat=ast, line=1.5)"
    },
    {
      "created_at": "2026-04-26T23:03:40.186924+00:00",
      "sport": "basketball_nba",
      "event_id": "62dc6619019d4366984883a71b283077",
      "selection": "Nikola Vucevic OVER 1.5 ast",
      "market_type": "PROP",
      "line": 1.5,
      "odds": null,
      "edge_pct": null,
      "units": null,
      "reason": "PROP_PLAYOFF_ROLE_GATE_SHADOW (v25.90, pts_avg=10.0 < 12.0, stat=ast, line=1.5)"
    },
    {
      "created_at": "2026-04-26T23:03:39.940076+00:00",
      "sport": "basketball_nba",
      "event_id": "62dc6619019d4366984883a71b283077",
      "selection": "Neemias Queta OVER 1.5 ast",
      "market_type": "PROP",
      "line": 1.5,
      "odds": null,
      "edge_pct": null,
      "units": null,
      "reason": "PROP_PLAYOFF_ROLE_GATE_SHADOW (v25.90, pts_avg=10.4 < 12.0, stat=ast, line=1.5)"
    },
    {
      "created_at": "2026-04-26T23:03:35.020730+00:00",
      "sport": "basketball_nba",
      "event_id": "62dc6619019d4366984883a71b283077",
      "selection": "Derrick White OVER 3.5 reb",
      "market_type": "PROP",
      "line": 3.5,
      "odds": null,
      "edge_pct": null,
      "units": null,
      "reason": "PROP_PLAYOFF_ROLE_GATE_SHADOW (v25.90, pts_avg=11.9 < 12.0, stat=reb, line=3.5)"
    },
    {
      "created_at": "2026-04-26T23:03:34.040236+00:00",
      "sport": "basketball_nba",
      "event_id": "62dc6619019d4366984883a71b283077",
      "selection": "Neemias Queta OVER 7.5 reb",
      "market_type": "PROP",
      "line": 7.5,
      "odds": null,
      "edge_pct": null,
      "units": null,
      "reason": "PROP_PLAYOFF_ROLE_GATE_SHADOW (v25.90, pts_avg=10.4 < 12.0, stat=reb, line=7.5)"
    },
    {
      "created_at": "2026-04-26T23:03:33.714732+00:00",
      "sport": "basketball_nba",
      "event_id": "62dc6619019d4366984883a71b283077",
      "selection": "Nikola Vucevic OVER 5.5 reb",
      "market_type": "PROP",
      "line": 5.5,
      "odds": null,
      "edge_pct": null,
      "units": null,
      "reason": "PROP_PLAYOFF_ROLE_GATE_SHADOW (v25.90, pts_avg=10.0 < 12.0, stat=reb, line=5.5)"
    },
    {
      "created_at": "2026-04-26T23:03:32.445134+00:00",
      "sport": "basketball_nba",
      "event_id": "62dc6619019d4366984883a71b283077",
      "selection": "Quentin Grimes OVER 5.5 pts",
      "market_type": "PROP",
      "line": 5.5,
      "odds": -134.0,
      "edge_pct": null,
      "units": null,
      "reason": "PROP_CAREER_FADE_FLIP (career=12.5, mkt=6.5, gap=6.0)"
    },
    {
      "created_at": "2026-04-26T23:03:32.444286+00:00",
      "sport": "basketball_nba",
      "event_id": "62dc6619019d4366984883a71b283077",
      "selection": "Quentin Grimes OVER 6.5 pts",
      "market_type": "PROP",
      "line": 6.5,
      "odds": null,
      "edge_pct": null,
      "units": null,
      "reason": "PROP_PLAYOFF_ROLE_GATE_SHADOW (v25.90, pts_avg=10.6 < 12.0, stat=pts, line=6.5)"
    },
    {
      "created_at": "2026-04-26T23:03:31.915987+00:00",
      "sport": "basketball_nba",
      "event_id": "62dc6619019d4366984883a71b283077",
      "selection": "Andre Drummond OVER 3.5 pts",
      "market_type": "PROP",
      "line": 3.5,
      "odds": null,
      "edge_pct": null,
      "units": null,
      "reason": "PROP_PLAYOFF_ROLE_GATE_SHADOW (v25.90, pts_avg=7.2 < 12.0, stat=pts, line=3.5)"
    },
    {
      "created_at": "2026-04-26T23:03:31.558231+00:00",
      "sport": "basketball_nba",
      "event_id": "62dc6619019d4366984883a71b283077",
      "selection": "Derrick White OVER 13.5 pts",
      "market_type": "PROP",
      "line": 13.5,
      "odds": -125.0,
      "edge_pct": null,
      "units": null,
      "reason": "PROP_CAREER_FADE_FLIP (career=16.2, mkt=13.5, gap=2.7)"
    },
    {
      "created_at": "2026-04-26T23:03:31.557605+00:00",
      "sport": "basketball_nba",
      "event_id": "62dc6619019d4366984883a71b283077",
      "selection": "Derrick White OVER 13.5 pts",
      "market_type": "PROP",
      "line": 13.5,
      "odds": -115.0,
      "edge_pct": null,
      "units": null,
      "reason": "PROP_CAREER_FADE_FLIP (career=16.2, mkt=13.5, gap=2.7)"
    },
    {
      "created_at": "2026-04-26T23:03:31.556674+00:00",
      "sport": "basketball_nba",
      "event_id": "62dc6619019d4366984883a71b283077",
      "selection": "Derrick White OVER 13.5 pts",
      "market_type": "PROP",
      "line": 13.5,
      "odds": null,
      "edge_pct": null,
      "units": null,
      "reason": "PROP_PLAYOFF_ROLE_GATE_SHADOW (v25.90, pts_avg=11.9 < 12.0, stat=pts, line=13.5)"
    },
    {
      "created_at": "2026-04-26T23:03:30.982212+00:00",
      "sport": "basketball_nba",
      "event_id": "62dc6619019d4366984883a71b283077",
      "selection": "Nikola Vucevic OVER 7.5 pts",
      "market_type": "PROP",
      "line": 7.5,
      "odds": -129.0,
      "edge_pct": null,
      "units": null,
      "reason": "PROP_CAREER_FADE_FLIP (career=16.7, mkt=7.8, gap=8.9)"
    },
    {
      "created_at": "2026-04-26T23:03:30.981559+00:00",
      "sport": "basketball_nba",
      "event_id": "62dc6619019d4366984883a71b283077",
      "selection": "Nikola Vucevic OVER 7.5 pts",
      "market_type": "PROP",
      "line": 7.5,
      "odds": -125.0,
      "edge_pct": null,
      "units": null,
      "reason": "PROP_CAREER_FADE_FLIP (career=16.7, mkt=7.8, gap=8.9)"
    },
    {
      "created_at": "2026-04-26T23:03:30.965191+00:00",
      "sport": "basketball_nba",
      "event_id": "62dc6619019d4366984883a71b283077",
      "selection": "Nikola Vucevic OVER 7.5 pts",
      "market_type": "PROP",
      "line": 7.5,
      "odds": null,
      "edge_pct": null,
      "units": null,
      "reason": "PROP_PLAYOFF_ROLE_GATE_SHADOW (v25.90, pts_avg=10.0 < 12.0, stat=pts, line=7.5)"
    },
    {
      "created_at": "2026-04-26T23:03:30.631789+00:00",
      "sport": "basketball_nba",
      "event_id": "62dc6619019d4366984883a71b283077",
      "selection": "Neemias Queta OVER 8.5 pts",
      "market_type": "PROP",
      "line": 8.5,
      "odds": null,
      "edge_pct": null,
      "units": null,
      "reason": "PROP_PLAYOFF_ROLE_GATE_SHADOW (v25.90, pts_avg=10.4 < 12.0, stat=pts, line=8.5)"
    },
    {
      "created_at": "2026-04-26T23:03:30.262215+00:00",
      "sport": "basketball_nba",
      "event_id": "62dc6619019d4366984883a71b283077",
      "selection": "Tyrese Maxey OVER 25.5 pts",
      "market_type": "PROP",
      "line": 25.5,
      "odds": -113.0,
      "edge_pct": null,
      "units": null,
      "reason": "PROP_CAREER_FADE_FLIP (career=27.2, mkt=25.5, gap=1.7)"
    },
    {
      "created_at": "2026-04-26T23:03:30.261774+00:00",
      "sport": "basketball_nba",
      "event_id": "62dc6619019d4366984883a71b283077",
      "selection": "Tyrese Maxey OVER 25.5 pts",
      "market_type": "PROP",
      "line": 25.5,
      "odds": -112.0,
      "edge_pct": null,
      "units": null,
      "reason": "PROP_CAREER_FADE_FLIP (career=27.2, mkt=25.5, gap=1.7)"
    },
    {
      "created_at": "2026-04-26T23:03:30.260875+00:00",
      "sport": "basketball_nba",
      "event_id": "62dc6619019d4366984883a71b283077",
      "selection": "Tyrese Maxey OVER 25.5 pts",
      "market_type": "PROP",
      "line": 25.5,
      "odds": -110.0,
      "edge_pct": null,
      "units": null,
      "reason": "PROP_CAREER_FADE_FLIP (career=27.2, mkt=25.5, gap=1.7)"
    },
    {
      "created_at": "2026-04-26T23:03:29.947617+00:00",
      "sport": "basketball_nba",
      "event_id": "62dc6619019d4366984883a71b283077",
      "selection": "Payton Pritchard OVER 12.5 pts",
      "market_type": "PROP",
      "line": 12.5,
      "odds": -121.0,
      "edge_pct": null,
      "units": null,
      "reason": "PROP_DIVERGENCE_GATE (proj=15.8 vs market_median=12.5, gap=3.3 > thr 3.0, books=4)"
    },
    {
      "created_at": "2026-04-26T23:03:29.947101+00:00",
      "sport": "basketball_nba",
      "event_id": "62dc6619019d4366984883a71b283077",
      "selection": "Payton Pritchard OVER 12.5 pts",
      "market_type": "PROP",
      "line": 12.5,
      "odds": -113.0,
      "edge_pct": null,
      "units": null,
      "reason": "PROP_DIVERGENCE_GATE (proj=15.8 vs market_median=12.5, gap=3.3 > thr 3.0, books=4)"
    },
    {
      "created_at": "2026-04-26T23:03:29.946362+00:00",
      "sport": "basketball_nba",
      "event_id": "62dc6619019d4366984883a71b283077",
      "selection": "Payton Pritchard OVER 12.5 pts",
      "market_type": "PROP",
      "line": 12.5,
      "odds": -121.0,
      "edge_pct": null,
      "units": null,
      "reason": "PROP_DIVERGENCE_GATE (proj=15.8 vs market_median=12.5, gap=3.3 > thr 3.0, books=4)"
    },
    {
      "created_at": "2026-04-26T23:03:29.945580+00:00",
      "sport": "basketball_nba",
      "event_id": "62dc6619019d4366984883a71b283077",
      "selection": "Payton Pritchard OVER 12.5 pts",
      "market_type": "PROP",
      "line": 12.5,
      "odds": -135.0,
      "edge_pct": null,
      "units": null,
      "reason": "PROP_DIVERGENCE_GATE (proj=15.8 vs market_median=12.5, gap=3.3 > thr 3.0, books=4)"
    },
    {
      "created_at": "2026-04-26T23:03:28.171682+00:00",
      "sport": "basketball_nba",
      "event_id": "62dc6619019d4366984883a71b283077",
      "selection": "Derrick White OVER 4.5 ast",
      "market_type": "PROP",
      "line": 4.5,
      "odds": null,
      "edge_pct": null,
      "units": null,
      "reason": "PROP_PLAYOFF_ROLE_GATE_SHADOW (v25.90, pts_avg=11.9 < 12.0, stat=ast, line=4.5)"
    },
    {
      "created_at": "2026-04-26T22:05:10.226359+00:00",
      "sport": "basketball_nba",
      "event_id": "399d2e69e4408801d09e614c88779989",
      "selection": "Josh Okogie OVER 2.5 pts",
      "market_type": "PROP",
      "line": 2.5,
      "odds": null,
      "edge_pct": null,
      "units": null,
      "reason": "PROP_PLAYOFF_ROLE_GATE_SHADOW (v25.90, pts_avg=3.6 < 12.0, stat=pts, line=2.5)"
    },
    {
      "created_at": "2026-04-26T22:05:10.001051+00:00",
      "sport": "basketball_nba",
      "event_id": "399d2e69e4408801d09e614c88779989",
      "selection": "Bronny James OVER 1.5 pts",
      "market_type": "PROP",
      "line": 1.5,
      "odds": null,
      "edge_pct": null,
      "units": null,
      "reason": "PROP_PLAYOFF_ROLE_GATE_SHADOW (v25.90, pts_avg=4.2 < 12.0, stat=pts, line=1.5)"
    },
    {
      "created_at": "2026-04-26T22:05:07.465241+00:00",
      "sport": "basketball_nba",
      "event_id": "399d2e69e4408801d09e614c88779989",
      "selection": "Marcus Smart OVER 2.5 reb",
      "market_type": "PROP",
      "line": 2.5,
      "odds": null,
      "edge_pct": null,
      "units": null,
      "reason": "PROP_PLAYOFF_ROLE_GATE_SHADOW (v25.90, pts_avg=11.5 < 12.0, stat=reb, line=2.5)"
    },
    {
      "created_at": "2026-04-26T22:05:06.991298+00:00",
      "sport": "basketball_nba",
      "event_id": "399d2e69e4408801d09e614c88779989",
      "selection": "Jaxson Hayes OVER 3.5 reb",
      "market_type": "PROP",
      "line": 3.5,
      "odds": null,
      "edge_pct": null,
      "units": null,
      "reason": "PROP_PLAYOFF_ROLE_GATE_SHADOW (v25.90, pts_avg=9.7 < 12.0, stat=reb, line=3.5)"
    },
    {
      "created_at": "2026-04-26T22:05:06.730507+00:00",
      "sport": "basketball_nba",
      "event_id": "399d2e69e4408801d09e614c88779989",
      "selection": "Luke Kennard OVER 4.5 reb",
      "market_type": "PROP",
      "line": 4.5,
      "odds": null,
      "edge_pct": null,
      "units": null,
      "reason": "PROP_PLAYOFF_ROLE_GATE_SHADOW (v25.90, pts_avg=11.9 < 12.0, stat=reb, line=4.5)"
    },
    {
      "created_at": "2026-04-26T22:05:06.469601+00:00",
      "sport": "basketball_nba",
      "event_id": "399d2e69e4408801d09e614c88779989",
      "selection": "Tari Eason OVER 7.5 reb",
      "market_type": "PROP",
      "line": 7.5,
      "odds": null,
      "edge_pct": null,
      "units": null,
      "reason": "PROP_PLAYOFF_ROLE_GATE_SHADOW (v25.90, pts_avg=10.2 < 12.0, stat=reb, line=7.5)"
    },
    {
      "created_at": "2026-04-26T22:05:05.590562+00:00",
      "sport": "basketball_nba",
      "event_id": "399d2e69e4408801d09e614c88779989",
      "selection": "Jaxson Hayes OVER 6.5 pts",
      "market_type": "PROP",
      "line": 6.5,
      "odds": null,
      "edge_pct": null,
      "units": null,
      "reason": "PROP_PLAYOFF_ROLE_GATE_SHADOW (v25.90, pts_avg=9.7 < 12.0, stat=pts, line=6.5)"
    },
    {
      "created_at": "2026-04-26T22:05:05.368288+00:00",
      "sport": "basketball_nba",
      "event_id": "399d2e69e4408801d09e614c88779989",
      "selection": "Marcus Smart OVER 11.5 pts",
      "market_type": "PROP",
      "line": 11.5,
      "odds": null,
      "edge_pct": null,
      "units": null,
      "reason": "PROP_PLAYOFF_ROLE_GATE_SHADOW (v25.90, pts_avg=11.5 < 12.0, stat=pts, line=11.5)"
    },
    {
      "created_at": "2026-04-26T22:05:05.142058+00:00",
      "sport": "basketball_nba",
      "event_id": "399d2e69e4408801d09e614c88779989",
      "selection": "Luke Kennard OVER 12.5 pts",
      "market_type": "PROP",
      "line": 12.5,
      "odds": null,
      "edge_pct": null,
      "units": null,
      "reason": "PROP_PLAYOFF_ROLE_GATE_SHADOW (v25.90, pts_avg=11.9 < 12.0, stat=pts, line=12.5)"
    },
    {
      "created_at": "2026-04-26T22:05:04.784907+00:00",
      "sport": "basketball_nba",
      "event_id": "399d2e69e4408801d09e614c88779989",
      "selection": "Tari Eason UNDER 13.5 pts",
      "market_type": "PROP",
      "line": 13.5,
      "odds": -125.0,
      "edge_pct": null,
      "units": null,
      "reason": "PROP_DIVERGENCE_GATE (proj=10.1 vs market_median=13.5, gap=3.4 > thr 3.0, books=4)"
    },
    {
      "created_at": "2026-04-26T22:05:04.664389+00:00",
      "sport": "basketball_nba",
      "event_id": "399d2e69e4408801d09e614c88779989",
      "selection": "Tari Eason OVER 13.5 pts",
      "market_type": "PROP",
      "line": 13.5,
      "odds": null,
      "edge_pct": null,
      "units": null,
      "reason": "PROP_PLAYOFF_ROLE_GATE_SHADOW (v25.90, pts_avg=10.2 < 12.0, stat=pts, line=13.5)"
    },
    {
      "created_at": "2026-04-26T22:05:03.536552+00:00",
      "sport": "basketball_nba",
      "event_id": "399d2e69e4408801d09e614c88779989",
      "selection": "Luke Kennard OVER 2.5 ast",
      "market_type": "PROP",
      "line": 2.5,
      "odds": null,
      "edge_pct": null,
      "units": null,
      "reason": "PROP_PLAYOFF_ROLE_GATE_SHADOW (v25.90, pts_avg=11.9 < 12.0, stat=ast, line=2.5)"
    },
    {
      "created_at": "2026-04-26T22:05:03.324161+00:00",
      "sport": "basketball_nba",
      "event_id": "399d2e69e4408801d09e614c88779989",
      "selection": "Marcus Smart OVER 4.5 ast",
      "market_type": "PROP",
      "line": 4.5,
      "odds": null,
      "edge_pct": null,
      "units": null,
      "reason": "PROP_PLAYOFF_ROLE_GATE_SHADOW (v25.90, pts_avg=11.5 < 12.0, stat=ast, line=4.5)"
    },
    {
      "created_at": "2026-04-26T22:04:55.926617+00:00",
      "sport": "basketball_nba",
      "event_id": "62dc6619019d4366984883a71b283077",
      "selection": "Nikola Vucevic OVER 1.5 ast",
      "market_type": "PROP",
      "line": 1.5,
      "odds": null,
      "edge_pct": null,
      "units": null,
      "reason": "PROP_PLAYOFF_ROLE_GATE_SHADOW (v25.90, pts_avg=10.0 < 12.0, stat=ast, line=1.5)"
    },
    {
      "created_at": "2026-04-26T22:04:55.709995+00:00",
      "sport": "basketball_nba",
      "event_id": "62dc6619019d4366984883a71b283077",
      "selection": "Neemias Queta OVER 1.5 ast",
      "market_type": "PROP",
      "line": 1.5,
      "odds": null,
      "edge_pct": null,
      "units": null,
      "reason": "PROP_PLAYOFF_ROLE_GATE_SHADOW (v25.90, pts_avg=10.4 < 12.0, stat=ast, line=1.5)"
    },
    {
      "created_at": "2026-04-26T22:04:53.089249+00:00",
      "sport": "basketball_nba",
      "event_id": "62dc6619019d4366984883a71b283077",
      "selection": "Derrick White OVER 3.5 reb",
      "market_type": "PROP",
      "line": 3.5,
      "odds": null,
      "edge_pct": null,
      "units": null,
      "reason": "PROP_PLAYOFF_ROLE_GATE_SHADOW (v25.90, pts_avg=11.9 < 12.0, stat=reb, line=3.5)"
    },
    {
      "created_at": "2026-04-26T22:04:52.392432+00:00",
      "sport": "basketball_nba",
      "event_id": "62dc6619019d4366984883a71b283077",
      "selection": "Neemias Queta OVER 7.5 reb",
      "market_type": "PROP",
      "line": 7.5,
      "odds": null,
      "edge_pct": null,
      "units": null,
      "reason": "PROP_PLAYOFF_ROLE_GATE_SHADOW (v25.90, pts_avg=10.4 < 12.0, stat=reb, line=7.5)"
    },
    {
      "created_at": "2026-04-26T22:04:51.924852+00:00",
      "sport": "basketball_nba",
      "event_id": "62dc6619019d4366984883a71b283077",
      "selection": "Nikola Vucevic OVER 4.5 reb",
      "market_type": "PROP",
      "line": 4.5,
      "odds": -143.0,
      "edge_pct": null,
      "units": null,
      "reason": "PROP_CAREER_FADE_FLIP (career=9.3, mkt=5.5, gap=3.8)"
    },
    {
      "created_at": "2026-04-26T22:04:51.924315+00:00",
      "sport": "basketball_nba",
      "event_id": "62dc6619019d4366984883a71b283077",
      "selection": "Nikola Vucevic OVER 5.5 reb",
      "market_type": "PROP",
      "line": 5.5,
      "odds": null,
      "edge_pct": null,
      "units": null,
      "reason": "PROP_PLAYOFF_ROLE_GATE_SHADOW (v25.90, pts_avg=10.0 < 12.0, stat=reb, line=5.5)"
    },
    {
      "created_at": "2026-04-26T22:04:51.272616+00:00",
      "sport": "basketball_nba",
      "event_id": "62dc6619019d4366984883a71b283077",
      "selection": "Derrick White OVER 13.5 pts",
      "market_type": "PROP",
      "line": 13.5,
      "odds": -121.0,
      "edge_pct": null,
      "units": null,
      "reason": "PROP_CAREER_FADE_FLIP (career=16.2, mkt=13.5, gap=2.7)"
    },
    {
      "created_at": "2026-04-26T22:04:51.272023+00:00",
      "sport": "basketball_nba",
      "event_id": "62dc6619019d4366984883a71b283077",
      "selection": "Derrick White OVER 13.5 pts",
      "market_type": "PROP",
      "line": 13.5,
      "odds": -113.0,
      "edge_pct": null,
      "units": null,
      "reason": "PROP_CAREER_FADE_FLIP (career=16.2, mkt=13.5, gap=2.7)"
    },
    {
      "created_at": "2026-04-26T22:04:51.270865+00:00",
      "sport": "basketball_nba",
      "event_id": "62dc6619019d4366984883a71b283077",
      "selection": "Derrick White OVER 13.5 pts",
      "market_type": "PROP",
      "line": 13.5,
      "odds": -122.0,
      "edge_pct": null,
      "units": null,
      "reason": "PROP_CAREER_FADE_FLIP (career=16.2, mkt=13.5, gap=2.7)"
    },
    {
      "created_at": "2026-04-26T22:04:51.269737+00:00",
      "sport": "basketball_nba",
      "event_id": "62dc6619019d4366984883a71b283077",
      "selection": "Derrick White OVER 13.5 pts",
      "market_type": "PROP",
      "line": 13.5,
      "odds": -111.0,
      "edge_pct": null,
      "units": null,
      "reason": "PROP_CAREER_FADE_FLIP (career=16.2, mkt=13.5, gap=2.7)"
    },
    {
      "created_at": "2026-04-26T22:04:51.268989+00:00",
      "sport": "basketball_nba",
      "event_id": "62dc6619019d4366984883a71b283077",
      "selection": "Derrick White OVER 13.5 pts",
      "market_type": "PROP",
      "line": 13.5,
      "odds": null,
      "edge_pct": null,
      "units": null,
      "reason": "PROP_PLAYOFF_ROLE_GATE_SHADOW (v25.90, pts_avg=11.9 < 12.0, stat=pts, line=13.5)"
    },
    {
      "created_at": "2026-04-26T22:04:51.039840+00:00",
      "sport": "basketball_nba",
      "event_id": "62dc6619019d4366984883a71b283077",
      "selection": "Nikola Vucevic OVER 7.5 pts",
      "market_type": "PROP",
      "line": 7.5,
      "odds": -129.0,
      "edge_pct": null,
      "units": null,
      "reason": "PROP_CAREER_FADE_FLIP (career=16.7, mkt=7.8, gap=8.9)"
    },
    {
      "created_at": "2026-04-26T22:04:51.038980+00:00",
      "sport": "basketball_nba",
      "event_id": "62dc6619019d4366984883a71b283077",
      "selection": "Nikola Vucevic OVER 7.5 pts",
      "market_type": "PROP",
      "line": 7.5,
      "odds": -126.0,
      "edge_pct": null,
      "units": null,
      "reason": "PROP_CAREER_FADE_FLIP (career=16.7, mkt=7.8, gap=8.9)"
    },
    {
      "created_at": "2026-04-26T22:04:51.038056+00:00",
      "sport": "basketball_nba",
      "event_id": "62dc6619019d4366984883a71b283077",
      "selection": "Nikola Vucevic OVER 7.5 pts",
      "market_type": "PROP",
      "line": 7.5,
      "odds": -121.0,
      "edge_pct": null,
      "units": null,
      "reason": "PROP_CAREER_FADE_FLIP (career=16.7, mkt=7.5, gap=9.2)"
    },
    {
      "created_at": "2026-04-26T22:04:51.037447+00:00",
      "sport": "basketball_nba",
      "event_id": "62dc6619019d4366984883a71b283077",
      "selection": "Nikola Vucevic OVER 7.5 pts",
      "market_type": "PROP",
      "line": 7.5,
      "odds": -122.0,
      "edge_pct": null,
      "units": null,
      "reason": "PROP_CAREER_FADE_FLIP (career=16.7, mkt=7.8, gap=8.9)"
    },
    {
      "created_at": "2026-04-26T22:04:51.036615+00:00",
      "sport": "basketball_nba",
      "event_id": "62dc6619019d4366984883a71b283077",
      "selection": "Nikola Vucevic OVER 7.5 pts",
      "market_type": "PROP",
      "line": 7.5,
      "odds": null,
      "edge_pct": null,
      "units": null,
      "reason": "PROP_PLAYOFF_ROLE_GATE_SHADOW (v25.90, pts_avg=10.0 < 12.0, stat=pts, line=7.5)"
    },
    {
      "created_at": "2026-04-26T22:04:50.803906+00:00",
      "sport": "basketball_nba",
      "event_id": "62dc6619019d4366984883a71b283077",
      "selection": "Tyrese Maxey OVER 25.5 pts",
      "market_type": "PROP",
      "line": 25.5,
      "odds": -127.0,
      "edge_pct": null,
      "units": null,
      "reason": "PROP_CAREER_FADE_FLIP (career=27.2, mkt=25.5, gap=1.7)"
    },
    {
      "created_at": "2026-04-26T22:04:50.803360+00:00",
      "sport": "basketball_nba",
      "event_id": "62dc6619019d4366984883a71b283077",
      "selection": "Tyrese Maxey OVER 25.5 pts",
      "market_type": "PROP",
      "line": 25.5,
      "odds": -110.0,
      "edge_pct": null,
      "units": null,
      "reason": "PROP_CAREER_FADE_FLIP (career=27.2, mkt=25.5, gap=1.7)"
    },
    {
      "created_at": "2026-04-26T22:04:50.802400+00:00",
      "sport": "basketball_nba",
      "event_id": "62dc6619019d4366984883a71b283077",
      "selection": "Tyrese Maxey OVER 25.5 pts",
      "market_type": "PROP",
      "line": 25.5,
      "odds": -125.0,
      "edge_pct": null,
      "units": null,
      "reason": "PROP_CAREER_FADE_FLIP (career=27.2, mkt=25.5, gap=1.7)"
    },
    {
      "created_at": "2026-04-26T22:04:50.355535+00:00",
      "sport": "basketball_nba",
      "event_id": "62dc6619019d4366984883a71b283077",
      "selection": "Neemias Queta OVER 8.5 pts",
      "market_type": "PROP",
      "line": 8.5,
      "odds": null,
      "edge_pct": null,
      "units": null,
      "reason": "PROP_PLAYOFF_ROLE_GATE_SHADOW (v25.90, pts_avg=10.4 < 12.0, stat=pts, line=8.5)"
    },
    {
      "created_at": "2026-04-26T22:04:50.131806+00:00",
      "sport": "basketball_nba",
      "event_id": "62dc6619019d4366984883a71b283077",
      "selection": "Payton Pritchard OVER 12.5 pts",
      "market_type": "PROP",
      "line": 12.5,
      "odds": -127.0,
      "edge_pct": null,
      "units": null,
      "reason": "PROP_DIVERGENCE_GATE (proj=15.8 vs market_median=12.5, gap=3.3 > thr 3.0, books=4)"
    },
    {
      "created_at": "2026-04-26T22:04:50.130577+00:00",
      "sport": "basketball_nba",
      "event_id": "62dc6619019d4366984883a71b283077",
      "selection": "Payton Pritchard OVER 12.5 pts",
      "market_type": "PROP",
      "line": 12.5,
      "odds": -127.0,
      "edge_pct": null,
      "units": null,
      "reason": "PROP_DIVERGENCE_GATE (proj=15.8 vs market_median=12.5, gap=3.3 > thr 3.0, books=4)"
    },
    {
      "created_at": "2026-04-26T22:04:50.130130+00:00",
      "sport": "basketball_nba",
      "event_id": "62dc6619019d4366984883a71b283077",
      "selection": "Payton Pritchard OVER 12.5 pts",
      "market_type": "PROP",
      "line": 12.5,
      "odds": -127.0,
      "edge_pct": null,
      "units": null,
      "reason": "PROP_DIVERGENCE_GATE (proj=15.8 vs market_median=12.5, gap=3.3 > thr 3.0, books=4)"
    }
  ],
  "book_performance": [
    {
      "book": "FanDuel",
      "bets": 103,
      "wins": 60,
      "losses": 40,
      "pnl": 52.5,
      "wagered": 500.0,
      "avg_clv": 0.24
    },
    {
      "book": "Fanatics",
      "bets": 44,
      "wins": 28,
      "losses": 15,
      "pnl": 38.4,
      "wagered": 210.0,
      "avg_clv": 1.29
    },
    {
      "book": "Caesars",
      "bets": 62,
      "wins": 32,
      "losses": 26,
      "pnl": 33.6,
      "wagered": 299.5,
      "avg_clv": 0.95
    },
    {
      "book": "BetRivers",
      "bets": 66,
      "wins": 39,
      "losses": 26,
      "pnl": 32.0,
      "wagered": 326.0,
      "avg_clv": 0.06
    },
    {
      "book": "DraftKings",
      "bets": 126,
      "wins": 63,
      "losses": 62,
      "pnl": -12.4,
      "wagered": 622.5,
      "avg_clv": -0.46
    },
    {
      "book": "BetMGM",
      "bets": 69,
      "wins": 33,
      "losses": 36,
      "pnl": -50.2,
      "wagered": 336.5,
      "avg_clv": 0.27
    }
  ]
}